fable_py/__init__.py
fable_py/__main__.py
fable_py/kernel.py
fable_py/version.py
fable_py/images/logo-32x32.png
fable_py/images/logo-64x64.png
fable_py/images/logo-fable.png
fable_py-0.7.0.dist-info/LICENSE
fable_py-0.7.0.dist-info/METADATA
fable_py-0.7.0.dist-info/WHEEL
fable_py-0.7.0.dist-info/top_level.txt
fable_py-0.7.0.dist-info/RECORD
