Metadata-Version: 2.1
Name: fable-py
Version: 0.7.0
Summary: A Fable (python) kernel for Jupyter
Home-page: https://github.com/dbrattli/Fable.Jupyter
Author: Dag Brattli
Author-email: dag@brattli.net
License: UNKNOWN
Platform: UNKNOWN
Classifier: Framework :: IPython
Classifier: License :: OSI Approved :: MIT License
Classifier: Programming Language :: Python :: 3
Classifier: Programming Language :: F#
Classifier: Topic :: System :: Shells
License-File: LICENSE
Requires-Dist: jupyter
